MANIFEST.in
setup.py
powerutils/__init__.py
powerutils.egg-info/PKG-INFO
powerutils.egg-info/SOURCES.txt
powerutils.egg-info/dependency_links.txt
powerutils.egg-info/top_level.txt
powerutils/coilcraft/__init__.py
powerutils/coilcraft/coilcraft.py
powerutils/coilcraft/model/XAL5020-122.txt
powerutils/coilcraft/model/XAL5030-122.txt
powerutils/coilcraft/model/XAL5030-222.txt
powerutils/coilcraft/model/XAL5030-332.txt
powerutils/coilcraft/model/XAL5030-472.txt
powerutils/coilcraft/model/XAL5050-103.txt
powerutils/coilcraft/model/XAL5050-153.txt
powerutils/coilcraft/model/XAL5050-223.txt
powerutils/coilcraft/model/XAL5050-562.txt
powerutils/coilcraft/model/XAL5050-682.txt
powerutils/coilcraft/model/XAL5050-822.txt
powerutils/coilcraft/model/XAL6030-122.txt
powerutils/coilcraft/model/XAL6030-182.txt
powerutils/coilcraft/model/XAL6030-222.txt
powerutils/coilcraft/model/XAL6030-332.txt
powerutils/coilcraft/model/XAL6060-103.txt
powerutils/coilcraft/model/XAL6060-153.txt
powerutils/coilcraft/model/XAL6060-223.txt
powerutils/coilcraft/model/XAL6060-333.txt
powerutils/coilcraft/model/XAL6060-472.txt
powerutils/coilcraft/model/XAL6060-562.txt
powerutils/coilcraft/model/XAL6060-682.txt
powerutils/coilcraft/model/XAL6060-822.txt
powerutils/coilcraft/model/XAL7030-103.txt
powerutils/coilcraft/model/XAL7030-152.txt
powerutils/coilcraft/model/XAL7030-222.txt
powerutils/coilcraft/model/XAL7030-272.txt
powerutils/coilcraft/model/XAL7030-332.txt
powerutils/coilcraft/model/XAL7030-472.txt
powerutils/coilcraft/model/XAL7030-562.txt
powerutils/coilcraft/model/XAL7030-682.txt
powerutils/coilcraft/model/XAL7030-822.txt
powerutils/coilcraft/model/XAL7050-103.txt
powerutils/coilcraft/model/XAL7050-153.txt
powerutils/coilcraft/model/XAL7050-183.txt
powerutils/coilcraft/model/XAL7050-223.txt
powerutils/coilcraft/model/XAL7050-333.txt
powerutils/coilcraft/model/XAL7050-473.txt
powerutils/coilcraft/model/XAL7070-102.txt
powerutils/coilcraft/model/XAL7070-122.txt
powerutils/coilcraft/model/XAL7070-182.txt
powerutils/coilcraft/model/XAL7070-222.txt
powerutils/coilcraft/model/XAL7070-332.txt
