Metadata-Version: 1.0
Name: powerutils
Version: 1.1
Summary: A custom lib of power electronics
Home-page: UNKNOWN
Author: felix
Author-email: qiyu_sjtu@163.com
License: UNKNOWN
Platform: UNKNOWN
